User.py
fastauth.py
fastauth_iq-0.1.6.dist-info/METADATA
fastauth_iq-0.1.6.dist-info/WHEEL
fastauth_iq-0.1.6.dist-info/top_level.txt
fastauth_iq-0.1.6.dist-info/RECORD
